Workbook

Sheet Expense
A1: Date | B1: Month | C1: Items | D1: Expense | E1: Category | F1: Cost Type
A2: 44470 | B2: =TEXT(A2,"mmmm") -> October | C2: Medicine | D2: 2300 | E2: Essential | F2: Over Budget
A3: 44470 | B3: =TEXT(A3,"mmmm") -> October | C3: Online shopping | D3: 767 | E3: Non-essential | F3: Within Budget
A4: 44470 | B4: =TEXT(A4,"mmmm") -> October | C4: Other essential items | D4: 2500 | E4: Essential | F4: Over Budget
A5: 44473 | B5: =TEXT(A5,"mmmm") -> October | C5: Vegetables & Fruit | D5: 710 | E5: Essential | F5: Within Budget
A6: 44473 | B6: =TEXT(A6,"mmmm") -> October | C6: Fish & Chicken | D6: 760 | E6: Non-essential | F6: Over Budget
A7: 44476 | B7: =TEXT(A7,"mmmm") -> October | C7: Gifts | D7: 1900 | E7: Non-essential | F7: Within Budget
A8: 44477 | B8: =TEXT(A8,"mmmm") -> October | C8: Ordering food | D8: 450 | E8: Non-essential | F8: Within Budget
A9: 44484 | B9: =TEXT(A9,"mmmm") -> October | C9: Movie with friends | D9: 620 | E9: Non-essential | F9: Within Budget
A10: 44485 | B10: =TEXT(A10,"mmmm") -> October | C10: Mobile Bill Payment | D10: 470 | E10: Essential | F10: Within Budget
A11: 44487 | B11: =TEXT(A11,"mmmm") -> October | C11: Online shopping | D11: 970 | E11: Non-essential | F11: Within Budget
A12: 44487 | B12: =TEXT(A12,"mmmm") -> October | C12: Medicine | D12: 1075 | E12: Essential | F12: Within Budget
A13: 44488 | B13: =TEXT(A13,"mmmm") -> October | C13: Ordering food | D13: 489 | E13: Non-essential | F13: Within Budget
... A51: 44553 | B51: =TEXT(A51,"mmmm") -> December | C51: Vegetables & Fruit | D51: 450 | E51: Essential | F51: Within Budget
D52: =SUM(D2:D51) -> 57045.27

Sheet Tasks
B1: Task to Perform
B2: How many times has Priya done transactions on online shopping, ordering food and gifts?
B3: Calculate the total expenses against each distinct item.
B4: Arrange the item-wise total expense in descending order.
B5: Present the item-wise total expense through a chart that shows the expense of each item as a percentage of the total expense. Don’t take trip expenses into consideration.
B6: Present the expense pattern visually over 3 months.
B7: Add a new column to the data table, name it as “Category” and apply data validation with drop-down fields as “Essentials” and “Non-essentials”. Fill in the column.
B8: Add another new column and name it as “Cost Type”. For each item, if the expense is more than 2000, tag it as “Over budget”, else, tag it as “Within budget”.
B9: Mention the ways how Priya can reduce her expenses. Justify each point.

Sheet Sheet1
C1: Q1: How many times has Priya done transactions on online shopping, ordering food and gifts?
C3: 1. Online shopping: | D3: =COUNTIF(Expense!C:C,"Online shopping") -> 6
C4: 2. Ordering food: | D4: =COUNTIF(Expense!C:C,"Ordering food") -> 5
C5: 3. Gifts: | D5: =COUNTIF(Expense!C:C,"Gifts") -> 4
C6: Total: | D6: =SUM(D3:D5) -> 15
C10: Q2: Calculate the total expenses against each distinct item.
C12: Items | D12: Total Expenses
C13: Medicine | D13: =SUMIF(Expense!C:C,Sheet1!C13,Expense!D:D) -> 7775
C14: Online shopping | D14: =SUMIF(Expense!C:C,Sheet1!C14,Expense!D:D) -> 7464
C15: Other essential items | D15: =SUMIF(Expense!C:C,Sheet1!C15,Expense!D:D) -> 10194.1
C16: Vegetables & Fruit | D16: =SUMIF(Expense!C:C,Sheet1!C16,Expense!D:D) -> 3217
C17: Fish & Chicken | D17: =SUMIF(Expense!C:C,Sheet1!C17,Expense!D:D) -> 3342
C18: Gifts | D18: =SUMIF(Expense!C:C,Sheet1!C18,Expense!D:D) -> 5688
C19: Ordering food | D19: =SUMIF(Expense!C:C,Sheet1!C19,Expense!D:D) -> 1857
C20: Movie with friends | D20: =SUMIF(Expense!C:C,Sheet1!C20,Expense!D:D) -> 2586
C21: Mobile Bill Payment | D21: =SUMIF(Expense!C:C,Sheet1!C21,Expense!D:D) -> 1411.26
C22: Cab to office | D22: =SUMIF(Expense!C:C,Sheet1!C22,Expense!D:D) -> 1510.91
C23: Trip | D23: =SUMIF(Expense!C:C,Sheet1!C23,Expense!D:D) -> 12000
C26: Q3: Arrange the item-wise total expense in descending order.
C28: Items | D28: Total Expenses | E28: Expense
C29: Medicine | D29: =VALUE(SUMIF(Expense!C:C,Sheet1!C39,Expense!D:D)) -> 12000 | E29: 1411.26
C30: Online shopping | D30: =VALUE(SUMIF(Expense!C:C,Sheet1!C38,Expense!D:D)) -> 1510.91 | E30: 1510.91
C31: Other essential items | D31: =VALUE(SUMIF(Expense!C:C,Sheet1!C37,Expense!D:D)) -> 1411.26 | E31: 1857
C32: Vegetables & Fruit | D32: =VALUE(SUMIF(Expense!C:C,Sheet1!C36,Expense!D:D)) -> 2586 | E32: 2586
C33: Fish & Chicken | D33: =VALUE(SUMIF(Expense!C:C,Sheet1!C35,Expense!D:D)) -> 1857 | E33: 3217
C34: Gifts | D34: =VALUE(SUMIF(Expense!C:C,Sheet1!C34,Expense!D:D)) -> 5688 | E34: 3342
C35: Ordering food | D35: =VALUE(SUMIF(Expense!C:C,Sheet1!C33,Expense!D:D)) -> 3342 | E35: 5688
C36: Movie with friends | D36: =VALUE(SUMIF(Expense!C:C,Sheet1!C32,Expense!D:D)) -> 3217 | E36: 7464
C37: Mobile Bill Payment | D37: =VALUE(SUMIF(Expense!C:C,Sheet1!C31,Expense!D:D)) -> 10194.1 | E37: 7775
C38: Cab to office | D38: =VALUE(SUMIF(Expense!C:C,Sheet1!C30,Expense!D:D)) -> 7464 | E38: 10194.1
C39: Trip | D39: =VALUE(SUMIF(Expense!C:C,Sheet1!C29,Expense!D:D)) -> 7775 | E39: 12000
C42: Q4: Present the item-wise total expense through a chart that shows the expense of each item as a percentage of the total expense. Don’t take trip expenses into consideration.
C44: Items | D44: Total Expenses | E44: Percentage
C45: Medicine | D45: =SUMIF(Expense!C:C,Sheet1!C45,Expense!D:D) -> 7775 | E45: =D45/$D$56 -> 0.13629526
C46: Online shopping | D46: =SUMIF(Expense!C:C,Sheet1!C46,Expense!D:D) -> 7464 | E46: =D46/$D$56 -> 0.13084345
C47: Other essential items | D47: =SUMIF(Expense!C:C,Sheet1!C47,Expense!D:D) -> 10194.1 | E47: =D47/$D$56 -> 0.17870193
C48: Vegetables & Fruit | D48: =SUMIF(Expense!C:C,Sheet1!C48,Expense!D:D) -> 3217 | E48: =D48/$D$56 -> 0.056393808
C49: Fish & Chicken | D49: =SUMIF(Expense!C:C,Sheet1!C49,Expense!D:D) -> 3342 | E49: =D49/$D$56 -> 0.05858505
C50: Gifts | D50: =SUMIF(Expense!C:C,Sheet1!C50,Expense!D:D) -> 5688 | E50: =D50/$D$56 -> 0.099710283
C51: Ordering food | D51: =SUMIF(Expense!C:C,Sheet1!C51,Expense!D:D) -> 1857 | E51: =D51/$D$56 -> 0.032553093
C52: Movie with friends | D52: =SUMIF(Expense!C:C,Sheet1!C52,Expense!D:D) -> 2586 | E52: =D52/$D$56 -> 0.045332418
C53: Mobile Bill Payment | D53: =SUMIF(Expense!C:C,Sheet1!C53,Expense!D:D) -> 1411.26 | E53: =D53/$D$56 -> 0.024739299
C54: Cab to office | D54: =SUMIF(Expense!C:C,Sheet1!C54,Expense!D:D) -> 1510.91 | E54: =D54/$D$56 -> 0.026486157
C55: Trip | D55: =SUMIF(Expense!C:C,Sheet1!C55,Expense!D:D) -> 12000 | E55: =D55/$D$56 -> 0.21035925
D56: 57045.27
C59: Q5: Present the expense pattern visually over 3 months.
C61: Month | D61: Total Expense
C62: October | D62: =SUMIF(Expense!B2:B51,Sheet1!C62,Expense!D2:D51) -> 17443.37
C63: November | D63: =SUMIF(Expense!B3:B52,Sheet1!C63,Expense!D3:D52) -> 18764.27
C64: December | D64: =SUMIF(Expense!B4:B53,Sheet1!C64,Expense!D4:D53) -> 20837.63
C77: Q6: Add a new column to the data table, name it as “Category” and apply data validation with drop-down fields as “Essentials” and “Non-essentials”. Fill in the column.
C79: Date | D79: Items | E79: Expense | F79: Category
C80: 44470 | D80: Medicine | E80: 2300 | F80: Essential
C81: 44470 | D81: Online shopping | E81: 767 | F81: Non-essential
C82: 44470 | D82: Other essential items | E82: 2500 | F82: Essential
C83: 44473 | D83: Vegetables & Fruit | E83: 710 | F83: Essential
C84: 44473 | D84: Fish & Chicken | E84: 760 | F84: Non-essential
C85: 44476 | D85: Gifts | E85: 1900 | F85: Non-essential
C86: 44477 | D86: Ordering food | E86: 450 | F86: Non-essential
C87: 44484 | D87: Movie with friends | E87: 620 | F87: Non-essential
C88: 44485 | D88: Mobile Bill Payment | E88: 470 | F88: Essential
C89: 44487 | D89: Online shopping | E89: 970 | F89: Non-essential
C90: 44487 | D90: Medicine | E90: 1075 | F90: Essential
C91: 44488 | D91: Ordering food | E91: 489 | F91: Non-essential
... C129: 44553 | D129: Vegetables & Fruit | E129: 450 | F129: Essential
C132: Q7: Add another new column and name it as “Cost Type”. For each item, if the expense is more than 2000, tag it as “Over budget”, else, tag it as “Within budget”.
C134: Date | D134: Items | E134: Expense | F134: Cost Type
C135: 44470 | D135: Medicine | E135: 2300 | F135: Over Budget
C136: 44470 | D136: Online shopping | E136: 767 | F136: Within Budget
C137: 44470 | D137: Other essential items | E137: 2500 | F137: Over Budget
C138: 44473 | D138: Vegetables & Fruit | E138: 710 | F138: Within Budget
C139: 44473 | D139: Fish & Chicken | E139: 760 | F139: Over Budget
C140: 44476 | D140: Gifts | E140: 1900 | F140: Within Budget
C141: 44477 | D141: Ordering food | E141: 450 | F141: Within Budget
C142: 44484 | D142: Movie with friends | E142: 620 | F142: Within Budget
C143: 44485 | D143: Mobile Bill Payment | E143: 470 | F143: Within Budget
C144: 44487 | D144: Online shopping | E144: 970 | F144: Within Budget
C145: 44487 | D145: Medicine | E145: 1075 | F145: Within Budget
C146: 44488 | D146: Ordering food | E146: 489 | F146: Within Budget
... C184: 44553 | D184: Vegetables & Fruit | E184: 450 | F184: Within Budget
C187: Q8: Mention the ways how Priya can reduce her expenses. Justify each point.
C189: 1. Reduce unnecessary online shopping.
C190: 2. Limit food ordering and prefer home-cooked meals.
C191: 3. Control entertainment expenses like movies and outings.
C192: 4. Plan trips properly to avoid high travel expenses.
C193: 5. Maintain a monthly budget and track expenses regularly.
C194: 6. Use public transport or shared rides to reduce cab costs.
C195: 7. Focus more on essential expenses than luxury spending.
